codeindex/__init__.py
codeindex/client.py
codeindex/config.py
codeindex/database.py
codeindex/embeddings_generator.py
codeindex/exceptions.py
codeindex/node_runner.py
codeindex/query.py
codeindex/types.py
caicai_codeindex-0.3.2.dist-info/METADATA
caicai_codeindex-0.3.2.dist-info/WHEEL
caicai_codeindex-0.3.2.dist-info/top_level.txt
caicai_codeindex-0.3.2.dist-info/RECORD
