Metadata-Version: 2.4
Name: caicai-codeindex
Version: 0.3.2
Summary: CodeIndex Python SDK - Direct SQLite database access
Author-email: CodeIndex <opensource@example.com>
License: MIT
Project-URL: Homepage, https://github.com/LydiaCai1203/codeindex
Project-URL: Repository, https://github.com/LydiaCai1203/codeindex
Project-URL: Issues, https://github.com/LydiaCai1203/codeindex/issues
Keywords: codeindex,ast,code-index,tree-sitter,code-intelligence,semantic-search,sqlite
Requires-Python: >=3.9
Requires-Dist: numpy>=1.24.0
Requires-Dist: requests>=2.28.0
Provides-Extra: dev
Requires-Dist: pytest; extra == "dev"
Requires-Dist: mypy; extra == "dev"
Requires-Dist: black; extra == "dev"
